src/docker_nuke/__main__.py
hdocker_nuke-1.1.3.dist-info/METADATA
hdocker_nuke-1.1.3.dist-info/WHEEL
hdocker_nuke-1.1.3.dist-info/entry_points.txt
hdocker_nuke-1.1.3.dist-info/licenses/LICENSE
hdocker_nuke-1.1.3.dist-info/RECORD
