Metadata-Version: 2.4
Name: hdocker-nuke
Version: 1.1.3
Summary: Quickly `kill`, then `rm` a container
Project-URL: Homepage, https://github.com/hamolicious/docker-nuke
Project-URL: Issues, https://github.com/hamolicious/docker-nuke/issues
Author-email: hamolicious <hamolicious@hamolicious.net>
License-File: LICENSE
Classifier: License :: OSI Approved :: MIT License
Classifier: Operating System :: OS Independent
Classifier: Programming Language :: Python :: 3
Requires-Python: >=3.10
Requires-Dist: certifi==2024.8.30
Requires-Dist: charset-normalizer==3.3.2
Requires-Dist: docker==7.1.0
Requires-Dist: idna==3.10
Requires-Dist: requests==2.32.3
Requires-Dist: urllib3==2.2.3
